myra-0.1.1.dist-info/METADATA
myra-0.1.1.dist-info/WHEEL
myra-0.1.1.dist-info/licenses/LICENSE
myra/__init__.py
myra/myra.py
myra-0.1.1.dist-info/RECORD
