Metadata-Version: 2.1
Name: myra
Version: 0.1.1
Summary: A library to count the colors in an image.
Author-Email: daniel daum <daniel_daum@outlook.com>
License: MIT
Requires-Python: >=3.10
Requires-Dist: pillow>=9.5.0
